pollination/adaptive_comfort_map/__init__.py
pollination/adaptive_comfort_map/_comfort.py
pollination/adaptive_comfort_map/_dynamic.py
pollination/adaptive_comfort_map/_dynshade.py
pollination/adaptive_comfort_map/_energy.py
pollination/adaptive_comfort_map/_prepare_folder.py
pollination/adaptive_comfort_map/_radcontrib.py
pollination/adaptive_comfort_map/_radiance.py
pollination/adaptive_comfort_map/_shdcontrib.py
pollination/adaptive_comfort_map/_view_factor.py
pollination/adaptive_comfort_map/_view_factor_contribution.py
pollination/adaptive_comfort_map/entry.py
pollination_adaptive_comfort_map-0.9.3.dist-info/LICENSE
pollination_adaptive_comfort_map-0.9.3.dist-info/METADATA
pollination_adaptive_comfort_map-0.9.3.dist-info/WHEEL
pollination_adaptive_comfort_map-0.9.3.dist-info/top_level.txt
pollination_adaptive_comfort_map-0.9.3.dist-info/RECORD
