Metadata-Version: 2.1
Name: pollination-adaptive-comfort-map
Version: 0.9.3
Summary: Adaptive thermal comfort map for Pollination.
Home-page: https://github.com/pollination/adaptive-comfort-map
Author: ladybug-tools
Author-email: info@ladybug.tools
Maintainer: chris, ladybug-tools
Maintainer-email: chris@ladybug.tools, info@ladybug.tools
License: PolyForm Shield License 1.0.0, https://polyformproject.org/wp-content/uploads/2020/06/PolyForm-Shield-1.0.0.txt
Project-URL: icon, https://raw.githubusercontent.com/ladybug-tools/artwork/master/icons_components/honeybee/png/adaptivemap.png
Keywords: honeybee,ladybug-tools,thermal,comfort,adaptive
License-File: LICENSE
Requires-Dist: pollination-ladybug (>=0.2.3)
Requires-Dist: pollination-ladybug-comfort (>=0.5.6)
Requires-Dist: pollination-honeybee-radiance (>=0.22.60)
Requires-Dist: pollination-honeybee-radiance-postprocess (>=0.0.65)
Requires-Dist: pollination-honeybee-energy (>=0.7.3)
Requires-Dist: pollination-lbt-honeybee (>=0.1.14)
Requires-Dist: pollination-alias (>=0.11.8)
Requires-Dist: pollination-path (>=0.3.2)
Provides-Extra: viz
Requires-Dist: pollination-honeybee-display (>=0.1.17) ; extra == 'viz'
